zigpy_cli/__init__.py
zigpy_cli/__main__.py
zigpy_cli/cli.py
zigpy_cli/common.py
zigpy_cli/const.py
zigpy_cli/database.py
zigpy_cli/helpers.py
zigpy_cli/ota.py
zigpy_cli/pcap.py
zigpy_cli/radio.py
zigpy_cli-1.2.1.dist-info/licenses/LICENSE
zigpy_cli-1.2.1.dist-info/METADATA
zigpy_cli-1.2.1.dist-info/WHEEL
zigpy_cli-1.2.1.dist-info/entry_points.txt
zigpy_cli-1.2.1.dist-info/top_level.txt
zigpy_cli-1.2.1.dist-info/RECORD
