Metadata-Version: 2.4
Name: zigpy-cli
Version: 1.2.1
Summary: Unified command line interface for zigpy radios
Author-email: puddly <puddly3@gmail.com>
License: GPL-3.0
Project-URL: repository, https://github.com/zigpy/zigpy-cli
Requires-Python: >=3.8
License-File: LICENSE
Requires-Dist: click
Requires-Dist: coloredlogs
Requires-Dist: scapy
Requires-Dist: zigpy>=0.75.0
Requires-Dist: bellows>=0.43.0
Requires-Dist: zigpy-deconz>=0.21.0
Requires-Dist: zigpy-xbee>=0.18.0
Requires-Dist: zigpy-zboss>=1.1.0
Requires-Dist: zigpy-zigate>=0.11.0
Requires-Dist: zigpy-znp>=0.11.1
Provides-Extra: testing
Requires-Dist: pytest>=7.1.2; extra == "testing"
Requires-Dist: pytest-asyncio>=0.19.0; extra == "testing"
Requires-Dist: pytest-timeout>=2.1.0; extra == "testing"
Requires-Dist: pytest-mock>=3.8.2; extra == "testing"
Requires-Dist: pytest-cov>=3.0.0; extra == "testing"
Dynamic: license-file
